shiyunzi/.DS_Store
shiyunzi/__init__.py
shiyunzi/__init__.pyc
shiyunzi/main.pyc
shiyunzi/PJYSDK/PJYSDK.pyc
shiyunzi/PJYSDK/__init__.py
shiyunzi/PJYSDK/__init__.pyc
shiyunzi/PJYSDK/__pycache__/PJYSDK.cpython-313.pyc
shiyunzi/PJYSDK/__pycache__/__init__.cpython-313.pyc
shiyunzi/__pycache__/__init__.cpython-313.pyc
shiyunzi/__pycache__/main.cpython-313.pyc
shiyunzi/assets/.DS_Store
shiyunzi/assets/draw.svg
shiyunzi/assets/robot.svg
shiyunzi/assets/stable_diffusion.svg
shiyunzi/doubao/cookie_fetcher.pyc
shiyunzi/doubao/doubao_service.pyc
shiyunzi/doubao/fetcher.pyc
shiyunzi/doubao/request.pyc
shiyunzi/doubao/response.pyc
shiyunzi/doubao/session_pool.pyc
shiyunzi/doubao/__pycache__/cookie_fetcher.cpython-313.pyc
shiyunzi/doubao/__pycache__/doubao_service.cpython-313.pyc
shiyunzi/doubao/__pycache__/fetcher.cpython-313.pyc
shiyunzi/doubao/__pycache__/session_pool.cpython-313.pyc
shiyunzi/jimeng/cookies.json
shiyunzi/jimeng/jimeng_image_service.pyc
shiyunzi/jimeng/jimeng_login_service.pyc
shiyunzi/jimeng/jimeng_service.pyc
shiyunzi/jimeng/jimeng_video_service.pyc
shiyunzi/llm/doubao_util.pyc
shiyunzi/llm/genmini_util.pyc
shiyunzi/llm/image2text.pyc
shiyunzi/llm/stable_diffusion_text2image.pyc
shiyunzi/llm/text2text_util.pyc
shiyunzi/llm/__pycache__/doubao_util.cpython-313.pyc
shiyunzi/llm/__pycache__/genmini_util.cpython-313.pyc
shiyunzi/llm/__pycache__/image2text.cpython-313.pyc
shiyunzi/llm/__pycache__/stable_diffusion_text2image.cpython-313.pyc
shiyunzi/llm/__pycache__/text2text_util.cpython-313.pyc
shiyunzi/stickers/single.png
shiyunzi/utils/account_util.pyc
shiyunzi/utils/auth_util.pyc
shiyunzi/utils/config_util.pyc
shiyunzi/utils/download_util.pyc
shiyunzi/utils/log_util.pyc
shiyunzi/utils/models.pyc
shiyunzi/utils/music_util.pyc
shiyunzi/utils/path_util.pyc
shiyunzi/utils/stable_diffusion_util.pyc
shiyunzi/utils/sticker_util.pyc
shiyunzi/utils/task_manager.pyc
shiyunzi/utils/task_util.pyc
shiyunzi/utils/__pycache__/account_util.cpython-313.pyc
shiyunzi-3.1.29.dist-info/METADATA
shiyunzi-3.1.29.dist-info/WHEEL
shiyunzi-3.1.29.dist-info/entry_points.txt
shiyunzi-3.1.29.dist-info/top_level.txt
shiyunzi-3.1.29.dist-info/RECORD
