Metadata-Version: 2.4
Name: shiyunzi
Version: 3.1.29
Requires-Dist: Pillow>=9.5.0
Requires-Dist: PyQt6>=6.4.0
Requires-Dist: setuptools>=65.5.1
Requires-Dist: wheel>=0.38.4
Requires-Dist: runwayapi>=0.2.1
Requires-Dist: PJYSDK>=1.0.8
Requires-Dist: peewee>=3.16.2
Requires-Dist: openai>=1.3.7
Requires-Dist: moviepy==1.0.0
Requires-Dist: cakegeminiapi>=0.1.8
Requires-Dist: webuiapi>=0.0.1
Requires-Dist: ffmpeg-python>=0.2.0
Requires-Dist: requests-aws4auth>=1.2.0
Requires-Dist: aiohttp>=3.9.0
Requires-Dist: httpx>=0.25.0
Requires-Dist: fastapi>=0.104.0
Requires-Dist: playwright>=1.40.0
Requires-Dist: pydantic>=2.5.0
Requires-Dist: ffmpeg-binaries-compat>=1.0.1
Dynamic: requires-dist
